swapdf/__init__.py
swapdf/__main__.py
swapdf-0.9.9.dist-info/entry_points.txt
swapdf-0.9.9.dist-info/WHEEL
swapdf-0.9.9.dist-info/METADATA
swapdf-0.9.9.dist-info/RECORD
