Metadata-Version: 2.1
Name: swapdf
Version: 0.9.9
Summary: SWAP PDF pages after scan of a two-sided sheet pack through a one-sided feeder.
Home-page: https://pypi.org/project/swapdf
Author: Carlo Alessandro Verre
Author-email: carlo.alessandro.verre@gmail.com
Requires-Python: >=3.6
Classifier: Programming Language :: Python :: 3
Classifier: Programming Language :: Python :: 3.6
Classifier: Development Status :: 4 - Beta
Classifier: Environment :: Console
Classifier: Intended Audience :: End Users/Desktop
Classifier: License :: OSI Approved :: GNU General Public License v3 or later (GPLv3+)
Classifier: Operating System :: POSIX :: Linux
Requires-Dist: pdfrw
Requires-Dist: libfunx
